jogo_da_adivinhacao_renan_martins/__init__.py
jogo_da_adivinhacao_renan_martins/cartelas.py
jogo_da_adivinhacao_renan_martins/config.py
jogo_da_adivinhacao_renan_martins/exibicao.py
jogo_da_adivinhacao_renan_martins/main.py
jogo_da_adivinhacao_renan_martins/validacao.py
jogo_da_adivinhacao_renan_martins-0.1.11.dist-info/METADATA
jogo_da_adivinhacao_renan_martins-0.1.11.dist-info/WHEEL
jogo_da_adivinhacao_renan_martins-0.1.11.dist-info/entry_points.txt
jogo_da_adivinhacao_renan_martins-0.1.11.dist-info/RECORD
