Metadata-Version: 2.3
Name: jogo-da-adivinhacao-renan-martins
Version: 0.1.11
Summary: 
Author: Renan Martins
Author-email: renanrodm@gmail.com
Requires-Python: >=3.13,<4.0
Classifier: Programming Language :: Python :: 3
Classifier: Programming Language :: Python :: 3.13
